odoo10_addon_mail_log_message_to_process-10.0.1.0.0.99.dev3-py3.8-nspkg.pth
odoo/addons/mail_log_message_to_process/README.rst
odoo/addons/mail_log_message_to_process/__init__.py
odoo/addons/mail_log_message_to_process/__manifest__.py
odoo/addons/mail_log_message_to_process/i18n/ca.po
odoo/addons/mail_log_message_to_process/i18n/de.po
odoo/addons/mail_log_message_to_process/i18n/es.po
odoo/addons/mail_log_message_to_process/i18n/fr.po
odoo/addons/mail_log_message_to_process/i18n/it.po
odoo/addons/mail_log_message_to_process/i18n/mail_log_message_to_process.pot
odoo/addons/mail_log_message_to_process/i18n/pt_BR.po
odoo/addons/mail_log_message_to_process/i18n/pt_PT.po
odoo/addons/mail_log_message_to_process/i18n/sl.po
odoo/addons/mail_log_message_to_process/i18n/tr.po
odoo/addons/mail_log_message_to_process/models/__init__.py
odoo/addons/mail_log_message_to_process/models/mail_thread.py
odoo/addons/mail_log_message_to_process/static/description/icon.png
odoo10_addon_mail_log_message_to_process-10.0.1.0.0.99.dev3.dist-info/METADATA
odoo10_addon_mail_log_message_to_process-10.0.1.0.0.99.dev3.dist-info/WHEEL
odoo10_addon_mail_log_message_to_process-10.0.1.0.0.99.dev3.dist-info/namespace_packages.txt
odoo10_addon_mail_log_message_to_process-10.0.1.0.0.99.dev3.dist-info/top_level.txt
odoo10_addon_mail_log_message_to_process-10.0.1.0.0.99.dev3.dist-info/RECORD
